quantum_debugger/__init__.py
quantum_debugger/backends/__init__.py
quantum_debugger/backends/aws_backend.py
quantum_debugger/backends/base.py
quantum_debugger/backends/base_backend.py
quantum_debugger/backends/cupy_backend.py
quantum_debugger/backends/gpu_backend.py
quantum_debugger/backends/ibm_backend.py
quantum_debugger/backends/numba_backend.py
quantum_debugger/backends/numpy_backend.py
quantum_debugger/backends/sparse_backend.py
quantum_debugger/benchmarks/__init__.py
quantum_debugger/benchmarks/optimization_benchmarks.py
quantum_debugger/benchmarks/qml_benchmarks.py
quantum_debugger/benchmarks/report_generator.py
quantum_debugger/benchmarks/scalability_benchmarks.py
quantum_debugger/core/__init__.py
quantum_debugger/core/circuit.py
quantum_debugger/core/gates.py
quantum_debugger/core/quantum_state.py
quantum_debugger/debugger/__init__.py
quantum_debugger/debugger/breakpoints.py
quantum_debugger/debugger/debugger.py
quantum_debugger/debugger/inspector.py
quantum_debugger/gpu/__init__.py
quantum_debugger/gpu/memory.py
quantum_debugger/gpu/mixed_precision.py
quantum_debugger/gpu/multi_gpu.py
quantum_debugger/integrations/__init__.py
quantum_debugger/integrations/cirq_adapter.py
quantum_debugger/integrations/cirq_bridge.py
quantum_debugger/integrations/pennylane_bridge.py
quantum_debugger/integrations/qiskit_adapter.py
quantum_debugger/integrations/qiskit_bridge.py
quantum_debugger/mitigation/__init__.py
quantum_debugger/mitigation/zne.py
quantum_debugger/mitigation/core/__init__.py
quantum_debugger/mitigation/core/extrapolator.py
quantum_debugger/mitigation/core/folder.py
quantum_debugger/noise/__init__.py
quantum_debugger/noise/composite_noise.py
quantum_debugger/noise/hardware_profiles.py
quantum_debugger/noise/noise_helpers.py
quantum_debugger/noise/noise_models.py
quantum_debugger/noise/stochastic_sampler.py
quantum_debugger/optimization/__init__.py
quantum_debugger/optimization/circuit_compiler.py
quantum_debugger/optimization/gate_reduction.py
quantum_debugger-0.6.0.dist-info/licenses/AUTHORS.md
quantum_debugger-0.6.0.dist-info/licenses/LICENSE
quantum_debugger-0.6.0.dist-info/METADATA
quantum_debugger-0.6.0.dist-info/WHEEL
quantum_debugger-0.6.0.dist-info/top_level.txt
quantum_debugger-0.6.0.dist-info/RECORD
