Metadata-Version: 2.4
Name: quantum-debugger
Version: 0.6.0
Summary: Comprehensive quantum machine learning library with AutoML, GPU acceleration, advanced algorithms (QGANs, Quantum RL), transfer learning, and multi-framework support (Qiskit, PennyLane, Cirq, TensorFlow, PyTorch)
Home-page: https://github.com/Raunakg2005/quantum-debugger
Author: Raunak Kumar Gupta
Author-email: raunak.gupta@somaiya.edu
Project-URL: Bug Reports, https://github.com/Raunakg2005/quantum-debugger/issues
Project-URL: Source, https://github.com/Raunakg2005/quantum-debugger
Project-URL: Documentation, https://github.com/Raunakg2005/quantum-debugger#readme
Keywords: quantum computing debugging profiling quantum-circuit visualization qml vqe qaoa machine-learning
Classifier: Development Status :: 4 - Beta
Classifier: Intended Audience :: Science/Research
Classifier: Intended Audience :: Developers
Classifier: Topic :: Scientific/Engineering :: Physics
Classifier: Topic :: Scientific/Engineering :: Artificial Intelligence
Classifier: Topic :: Software Development :: Debuggers
Classifier: License :: OSI Approved :: MIT License
Classifier: Programming Language :: Python :: 3
Classifier: Programming Language :: Python :: 3.9
Classifier: Programming Language :: Python :: 3.10
Classifier: Programming Language :: Python :: 3.11
Classifier: Programming Language :: Python :: 3.12
Requires-Python: >=3.9
License-File: LICENSE
License-File: AUTHORS.md
Requires-Dist: numpy>=1.20.0
Requires-Dist: scipy>=1.7.0
Requires-Dist: matplotlib>=3.5.0
Provides-Extra: qiskit
Requires-Dist: qiskit>=1.0.0; extra == "qiskit"
Provides-Extra: pennylane
Requires-Dist: pennylane>=0.30.0; extra == "pennylane"
Provides-Extra: cirq
Requires-Dist: cirq>=1.0.0; extra == "cirq"
Provides-Extra: tensorflow
Requires-Dist: tensorflow>=2.10.0; extra == "tensorflow"
Provides-Extra: pytorch
Requires-Dist: torch>=1.13.0; extra == "pytorch"
Provides-Extra: ibm
Requires-Dist: qiskit-ibm-runtime>=0.15.0; extra == "ibm"
Provides-Extra: aws
Requires-Dist: amazon-braket-sdk>=1.50.0; extra == "aws"
Requires-Dist: boto3>=1.28.0; extra == "aws"
Provides-Extra: all
Requires-Dist: qiskit>=1.0.0; extra == "all"
Requires-Dist: pennylane>=0.30.0; extra == "all"
Requires-Dist: cirq>=1.0.0; extra == "all"
Requires-Dist: tensorflow>=2.10.0; extra == "all"
Requires-Dist: torch>=1.13.0; extra == "all"
Requires-Dist: scikit-learn>=1.0.0; extra == "all"
Requires-Dist: qiskit-ibm-runtime>=0.15.0; extra == "all"
Requires-Dist: amazon-braket-sdk>=1.50.0; extra == "all"
Provides-Extra: dev
Requires-Dist: pytest>=7.0.0; extra == "dev"
Requires-Dist: pytest-cov>=3.0.0; extra == "dev"
Requires-Dist: black>=22.0.0; extra == "dev"
Requires-Dist: flake8>=4.0.0; extra == "dev"
Requires-Dist: mypy>=0.990; extra == "dev"
Dynamic: author
Dynamic: author-email
Dynamic: classifier
Dynamic: description
Dynamic: description-content-type
Dynamic: home-page
Dynamic: keywords
Dynamic: license-file
Dynamic: project-url
Dynamic: provides-extra
Dynamic: requires-dist
Dynamic: requires-python
Dynamic: summary
